streamdatasetjson/__init__.py
streamdatasetjson/dataset.py
streamdatasetjson/datasetjson.py
streamdatasetjson/errors.py
streamdatasetjson/utils.py
tests/__init__.py
tests/test_dataset.py
tests/test_datasetjson.py
stream_dataset_json-0.1.5.dist-info/LICENSE
stream_dataset_json-0.1.5.dist-info/METADATA
stream_dataset_json-0.1.5.dist-info/WHEEL
stream_dataset_json-0.1.5.dist-info/top_level.txt
stream_dataset_json-0.1.5.dist-info/RECORD
