Metadata-Version: 2.1
Name: stream-dataset-json
Version: 0.1.5
Summary: Package to stream-read large dataset JSON files.
Home-page: https://github.com/Parexel/stream-dataset-json
Project-URL: Bug Tracker, https://github.com/Parexel/stream-dataset-json/issues
Project-URL: Changelog, https://github.com/Parexel/stream-dataset-json/releases
Classifier: Programming Language :: Python :: 3
Classifier: License :: OSI Approved :: BSD License
Classifier: Intended Audience :: Developers
Requires-Python: >=3.6
License-File: LICENSE
Requires-Dist: ijson
